pytiflash/__init__.py
pytiflash/main.py
pytiflashash-0.0.1.dist-info/METADATA
pytiflashash-0.0.1.dist-info/WHEEL
pytiflashash-0.0.1.dist-info/entry_points.txt
pytiflashash-0.0.1.dist-info/top_level.txt
pytiflashash-0.0.1.dist-info/RECORD
