Metadata-Version: 2.1
Name: pytiflashash
Version: 0.0.1
Summary: tiflash python 
Home-page: https://github.com/cove9988/pytiflash
Author: paulg
Author-email: cove9988@gmail.com
License: MIT
Platform: UNKNOWN
Classifier: License :: OSI Approved :: MIT License
Classifier: Programming Language :: Python :: 3
Classifier: Programming Language :: Python :: 3.8
